bacnet_scan_tool/__init__.py
bacnet_scan_tool/main.py
bacnet_scan_tool/models.py
bacnet_scan_tool/network_discover_ping.py
bacnet_scan_tool-0.1.0rc0.dist-info/METADATA
bacnet_scan_tool-0.1.0rc0.dist-info/WHEEL
bacnet_scan_tool-0.1.0rc0.dist-info/RECORD
