Metadata-Version: 2.3
Name: bacnet-scan-tool
Version: 0.1.0rc0
Summary: 
License: Apache 2.0
Author: C. Allwardt
Author-email: 3979063+craig8@users.noreply.github.com
Requires-Python: >=3.10,<4.0
Classifier: License :: Other/Proprietary License
Classifier: Programming Language :: Python :: 3
Classifier: Programming Language :: Python :: 3.10
Classifier: Programming Language :: Python :: 3.11
Classifier: Programming Language :: Python :: 3.12
Classifier: Programming Language :: Python :: 3.13
Requires-Dist: bac0 (>=2025.6.10,<2026.0.0)
Requires-Dist: bacpypes3 (>=0.0.102,<0.0.103)
Requires-Dist: click (>=8.1.8,<9.0.0)
Requires-Dist: fastapi (>=0.115.11,<0.116.0)
Requires-Dist: gevent (>=25.5.1,<26.0.0)
Requires-Dist: netifaces (>=0.11.0,<0.12.0)
Requires-Dist: protocol-proxy (>=v2.0.0rc1)
Requires-Dist: protocol-proxy-bacnet (>=v2.0.0rc2)
Requires-Dist: psutil (>=7.0.0,<8.0.0)
Requires-Dist: pydantic (>=2.10.6,<3.0.0)
Requires-Dist: python-multipart (>=0.0.20,<0.0.21)
Requires-Dist: rdflib (>=6.0,<7.0)
Requires-Dist: sqlmodel (>=0.0.8,<1.0.0)
Requires-Dist: uvicorn (>=0.34.0,<0.35.0)
